trapper/__init__.py
trapper/__main__.py
trapper/commands.py
trapper/version.py
trapper/common/__init__.py
trapper/common/constants.py
trapper/common/io.py
trapper/common/lazy.py
trapper/common/params.py
trapper/common/plugins.py
trapper/common/registrable.py
trapper/common/utils.py
trapper/common/notebook_utils/__init__.py
trapper/common/notebook_utils/file_transfer.py
trapper/common/notebook_utils/prepare_data.py
trapper/common/testing_utils/__init__.py
trapper/common/testing_utils/hf_datasets_caching.py
trapper/common/testing_utils/shell_utils.py
trapper/common/testing_utils/pytest_fixtures/__init__.py
trapper/common/testing_utils/pytest_fixtures/data.py
trapper/common/testing_utils/pytest_fixtures/training.py
trapper/data/__init__.py
trapper/data/data_collator.py
trapper/data/dataset_loader.py
trapper/data/dataset_reader.py
trapper/data/label_mapper.py
trapper/data/data_adapters/__init__.py
trapper/data/data_adapters/data_adapter.py
trapper/data/data_adapters/question_answering_adapter.py
trapper/data/data_processors/__init__.py
trapper/data/data_processors/data_processor.py
trapper/data/data_processors/squad/__init__.py
trapper/data/data_processors/squad/question_answering_processor.py
trapper/data/data_processors/squad/squad_processor.py
trapper/data/tokenizers/__init__.py
trapper/data/tokenizers/squad.py
trapper/data/tokenizers/tokenizer_wrapper.py
trapper/metrics/__init__.py
trapper/metrics/jury.py
trapper/metrics/metric.py
trapper/metrics/input_handlers/__init__.py
trapper/metrics/input_handlers/input_handler.py
trapper/metrics/input_handlers/language_generation_input_handler.py
trapper/metrics/input_handlers/question_answering_input_handler.py
trapper/metrics/input_handlers/token_classification_input_handler.py
trapper/metrics/output_handlers/__init__.py
trapper/metrics/output_handlers/output_handler.py
trapper/metrics/output_handlers/token_classification_output_handler.py
trapper/models/__init__.py
trapper/models/auto_wrappers.py
trapper-0.0.13.dist-info/LICENSE
trapper-0.0.13.dist-info/METADATA
trapper-0.0.13.dist-info/WHEEL
trapper-0.0.13.dist-info/entry_points.txt
trapper-0.0.13.dist-info/top_level.txt
trapper-0.0.13.dist-info/RECORD
