Metadata-Version: 2.1
Name: trapper
Version: 0.0.13
Summary: State-of-the-art NLP through transformer models in a modular design and consistent APIs.
Home-page: https://github.com/obss/trapper
Author: OBSS
Keywords: python,nlp,natural-language-processing,deep-learning,transformer,pytorch,transformers,allennlp,pytorch-transformers
Classifier: Operating System :: OS Independent
Classifier: Intended Audience :: Developers
Classifier: Intended Audience :: Science/Research
Classifier: Programming Language :: Python :: 3
Classifier: Programming Language :: Python :: 3.7
Classifier: Programming Language :: Python :: 3.8
Classifier: Programming Language :: Python :: 3.9
Classifier: Topic :: Software Development :: Libraries
Classifier: Topic :: Software Development :: Libraries :: Python Modules
Classifier: Topic :: Scientific/Engineering
Classifier: Topic :: Scientific/Engineering :: Artificial Intelligence
Requires-Python: >=3.7.1
License-File: LICENSE
Requires-Dist: allennlp (<2.11,>=2.10.0)
Requires-Dist: datasets (<2.5,>=2.3.0)
Requires-Dist: deepdiff (>=5.2.0)
Requires-Dist: jury (<2.3,>=2.2.3)
Requires-Dist: numpy (>=1.21.2)
Requires-Dist: seqeval (==1.2.2)
Requires-Dist: tensorboardX (==2.1)
Requires-Dist: transformers (<4.21,>=4.18)
Provides-Extra: dev
Requires-Dist: black (==22.3.0) ; extra == 'dev'
Requires-Dist: flake8 (==3.9.2) ; extra == 'dev'
Requires-Dist: isort (==5.9.2) ; extra == 'dev'
Requires-Dist: pytest (>=6.2.4) ; extra == 'dev'
Requires-Dist: pytest-cov (>=2.12.1) ; extra == 'dev'
Requires-Dist: pylint (>=2.11) ; extra == 'dev'
Requires-Dist: mypy (>=0.9) ; extra == 'dev'
Requires-Dist: importlib-metadata (<4.3,>=1.1.0) ; (python_version < "3.8") and extra == 'dev'
